composio/__init__.py
composio/__version__.py
composio/exceptions.py
composio/py.typed
composio/sdk.py
composio/types.py
composio/client/__init__.py
composio/client/types.py
composio/core/__init__.py
composio/core/types.py
composio/core/models/__init__.py
composio/core/models/_files.py
composio/core/models/_modifiers.py
composio/core/models/_telemetry.py
composio/core/models/auth_configs.py
composio/core/models/base.py
composio/core/models/connected_accounts.py
composio/core/models/custom_tools.py
composio/core/models/internal.py
composio/core/models/mcp.py
composio/core/models/tool_router.py
composio/core/models/toolkits.py
composio/core/models/tools.py
composio/core/models/triggers.py
composio/core/provider/__init__.py
composio/core/provider/_openai.py
composio/core/provider/_openai_responses.py
composio/core/provider/agentic.py
composio/core/provider/base.py
composio/core/provider/none_agentic.py
composio/integration_test/__init__.py
composio/integration_test/conftest.py
composio/integration_test/test_mcp.py
composio/utils/__init__.py
composio/utils/logging.py
composio/utils/mimetypes.py
composio/utils/openapi.py
composio/utils/pydantic.py
composio/utils/shared.py
composio/utils/toolkit_version.py
composio/utils/uuid.py
composio-0.10.7.dist-info/METADATA
composio-0.10.7.dist-info/WHEEL
composio-0.10.7.dist-info/top_level.txt
composio-0.10.7.dist-info/RECORD
