Metadata-Version: 2.4
Name: composio
Version: 0.10.7
Summary: SDK for integrating Composio with your applications.
Home-page: https://github.com/composiohq/composio
Author: Composio
Author-email: tech@composio.dev
Classifier: Programming Language :: Python :: 3
Classifier: License :: OSI Approved :: Apache Software License
Classifier: Operating System :: OS Independent
Requires-Python: >=3.9,<4
Requires-Dist: pysher>=1.0.8
Requires-Dist: pydantic>=2.6.4
Requires-Dist: composio-client==1.26.0
Requires-Dist: typing-extensions>=4.0.0
Requires-Dist: openai
Dynamic: author
Dynamic: author-email
Dynamic: home-page
Dynamic: requires-python
